Workbook

Sheet Lançamento
A1: CONTROLE DE GASTOS PESSOAIS
A3: ID | B3: Data | C3: Descrição | D3: Categoria | E3: Tipo | F3: Valor (R$) | G3: Observação
A4: 1 | B4: 46082 | C4: Supermercado | D4: Alimentação | E4: Despesa | F4: 1000 | G4: Compra Mensal
A5: 2 | B5: 46083 | C5: Uber | D5: Transporte | E5: Despesa | F5: 250 | G5: Transporte Mensal
A6: 3 | B6: 46084 | C6: Netflix | D6: Assinaturas | E6: Despesa | F6: 20.9 | G6: Entretenimento
A7: 4 | B7: 46086 | C7: Salário | D7: Outros | E7: Receita | F7: 4750 | G7: Salário de Março
A8: 5 | B8: 46087 | C8: Farmácia | D8: Saúde | E8: Despesa | F8: 96.5 | G8: Remédios
A9: 6 | B9: 46089 | C9: Aluguel | D9: Moradia | E9: Despesa | F9: 1100 | G9: Casa
A10: 7 | B10: 46091 | C10: Icloud | D10: Assinaturas | E10: Despesa | F10: 19.9 | G10: Entretenimento
A11: 8 | B11: 46093 | C11: Faculdade | D11: Educação | E11: Despesa | F11: 450 | G11: Estudos
A12: 9 | B12: 46096 | C12: Restaurante | D12: Alimentação | E12: Despesa | F12: 110 | G12: Almoço
A13: 10 | B13: 46099 | C13: Freelancer | D13: Outros | E13: Receita | F13: 500 | G13: Projeto PBI e Excel
A14: 11 | B14: 46101 | C14: Academia | D14: Saúde | E14: Despesa | F14: 99.99 | G14: Entretenimento
A15: 12 | B15: 46103 | C15: Cinema | D15: Lazer | E15: Despesa | F15: 48.5 | G15: Entretenimento
... A17: 14 | B17: 46106 | C17: Roupas | D17: Vestuários | E17: Despesa | F17: 250 | G17: Calças e blusas
A18: 15 | B18: 46109 | C18: Gasolina | D18: Transporte | E18: Despesa | F18: 180
A19: 16 | B19: 46109 | C19: Bar | D19: Lazer | E19: Despesa | F19: 350 | G19: Entretenimento
A20: 17 | B20: 46111 | C20: Tesouro Direto | D20: Investimento | E20: Despesa | F20: 400 | G20: Aporte Mensal

Sheet Resumo Mensal
B1: Resumo Mensal - Março 2026
B3: Visão Geral do Mês
B4: Total de Receitas | C4: =SUMIF(Lançamento!E3:E20,"Receita",Lançamento!F3:F20) -> 5250
B5: Total de Despesas | C5: =SUMIF(Lançamento!E4:E21,"Despesa",Lançamento!F4:F21) -> 4399.69
B6: Saldo do Mês | C6: =C4-C5 -> 850.31
B7: Nº Lançamentos | C7: =COUNTA(Lançamento!A4:A1048576) -> 17
B9: Despesas por Categoria
B10: Categoria | C10: Total Gasto | D10: % do Total
B11: Alimentação | C11: =SUM(Lançamento!F4,Lançamento!F12) -> 1110 | D11: =C11/C5 -> 0.2522905
B12: Transporte | C12: =SUM(Lançamento!F5,Lançamento!F18) -> 430 | D12: =C12/C5 -> 0.097734159
B13: Assinaturas | C13: =SUM(Lançamento!F6,Lançamento!F10,Lançamento!F16) -> 64.7 | D13: =C13/C5 -> 0.014705582
B14: Outros | C14: 0 | D14: 0
B15: Saúde | C15: =SUM(Lançamento!F8,Lançamento!F14) -> 196.49 | D15: =C15/C5 -> 0.044659965
B16: Moradia | C16: =SUM(Lançamento!F9) -> 1100 | D16: =C16/C5 -> 0.25001761
B17: Educação | C17: =SUM(Lançamento!F11) -> 450 | D17: =C17/C5 -> 0.10227993
B18: Lazer | C18: =SUM(Lançamento!F15,Lançamento!F19) -> 398.5 | D18: =C18/C5 -> 0.090574563
B19: Vestuários | C19: =SUM(Lançamento!F17) -> 250 | D19: =C19/C5 -> 0.056822185
B20: Investimentos | C20: =SUM(Lançamento!F20) -> 400 | D20: =C20/C5 -> 0.090915496
B21: Total Despesas | C21: =SUM(C11:C20) -> 4399.69 | D21: =SUM(D11:D20) -> 1

Sheet Dashboard
B1: DASHBOARD FINANCEIRO
B3: RECEITAS TOTAIS | D3: DESPESAS TOTAIS | F3: SALDO DO MÊS | H3: Nº LANÇAMENTOS
B4: =SUM('Resumo Mensal'!C4) -> 5250 | D4: =SUM('Resumo Mensal'!C5) -> 4399.69 | F4: =SUM('Resumo Mensal'!C6) -> 850.31 | H4: =SUM('Resumo Mensal'!C7) -> 17
L10: Categoria | M10: Valor
L11: Alimentação | M11: =SUM('Resumo Mensal'!C11) -> 1110
L12: Transporte | M12: =SUM('Resumo Mensal'!C12) -> 430
L13: Assinaturas | M13: =SUM('Resumo Mensal'!C13) -> 64.7
L14: Outros | M14: =SUM('Resumo Mensal'!C14) -> 0
L15: Saúde | M15: =SUM('Resumo Mensal'!C15) -> 196.49
L16: Moradia | M16: =SUM('Resumo Mensal'!C16) -> 1100
L17: Educação | M17: =SUM('Resumo Mensal'!C17) -> 450
L18: Lazer | M18: =SUM('Resumo Mensal'!C18) -> 398.5
L19: Vestuários | M19: =SUM('Resumo Mensal'!C19) -> 250
L20: Investimentos | M20: =SUM('Resumo Mensal'!C20) -> 400
